qhelper/__init__.py
qhelper/app.py
qhelper/auth.py
qhelper/client.cp310-win_amd64.pyd
qhelper/client.cp311-win_amd64.pyd
qhelper/client.cp39-win_amd64.pyd
qhelper/dash/app.py
qhelper/dash/pages/points.py
qhelper/error.py
qhelper/keys/public_key.pem
qhelper/pages/data.py
qhelper/pages/setting.py
qhelper/qmt.py
qhelper/routes.py
qhelper/run.py
qhelper/scheduler.py
qhelper/setting.py
qhelper/static/logo.jpg
qhelper/static/zsxq.png
qhelper/templates/auth.html
qhelper/templates/base.html
qhelper/templates/error.html
qhelper/templates/head.html
qhelper/templates/index.html
qhelper/templates/navbar.html
qhelper/templates/setting.html
qhelper/util.py
qhelper-0.2.11.dist-info/entry_points.txt
qhelper-0.2.11.dist-info/METADATA
qhelper-0.2.11.dist-info/WHEEL
qhelper-0.2.11.dist-info/RECORD
