Metadata-Version: 2.1
Name: qhelper
Version: 0.2.11
Summary: 
Author: mayuanchi
Author-email: mayuanchi1989@163.com
Requires-Python: >=3.9, !=2.7.*, !=3.0.*, !=3.1.*, !=3.2.*, !=3.3.*, !=3.4.*, !=3.5.*, !=3.6.*, !=3.7.*, !=3.8.*, !=3.12.*
Classifier: Programming Language :: Python :: 3
Classifier: Programming Language :: Python :: 3.9
Classifier: Programming Language :: Python :: 3.10
Classifier: Programming Language :: Python :: 3.11
Requires-Dist: akshare (>=1.14.1,<2.0.0)
Requires-Dist: appdirs (>=1.4.4,<2.0.0)
Requires-Dist: backtrader (>=1.9.78.123,<2.0.0.0)
Requires-Dist: bokeh (>=3.4.2,<4.0.0)
Requires-Dist: cryptography (>=42.0.8,<43.0.0)
Requires-Dist: dash (>=2.17.1,<3.0.0)
Requires-Dist: dask[complete] (>=2024.6.2,<2025.0.0)
Requires-Dist: distributed (>=2024.6.2,<2025.0.0)
Requires-Dist: flask (>=3.0.3,<4.0.0)
Requires-Dist: lowdb (>=0.0.1,<0.0.2)
Requires-Dist: pyarmor (>=8.5.9,<9.0.0)
Requires-Dist: pywencai (>=0.12.2,<0.13.0)
Requires-Dist: schedule (>=1.2.2,<2.0.0)
Requires-Dist: streamlit (>=1.36.0,<2.0.0)
Requires-Dist: xtquant (>=240613.1.1,<240614.0.0)
